{
  "name": "Turku",
  "x": 240460.6331,
  "y": 6711046.6297,
  "mapSheet": "L3",
  "meltCe": -9449.4052734375,
  "data": [
    {
      "year": -9250,
      "elevation": -124.928169250488,
      "meltBp": 11399.4052734375,
      "delta10BC": null
    },
    {
      "year": -9000,
      "elevation": -105.378768920898,
      "meltBp": 11399.4052734375,
      "delta10BC": 19.5494003296
    },
    {
      "year": -8750,
      "elevation": -90.2016296386719,
      "meltBp": 11399.4052734375,
      "delta10BC": 34.7265396118
    },
    {
      "year": -8500,
      "elevation": -85.9453125,
      "meltBp": 11399.4052734375,
      "delta10BC": 38.9828567505
    },
    {
      "year": -8250,
      "elevation": -93.9980773925781,
      "meltBp": 11399.4052734375,
      "delta10BC": 30.9300918579
    },
    {
      "year": -8000,
      "elevation": -82.7026748657227,
      "meltBp": 11399.4052734375,
      "delta10BC": 42.2254943848
    },
    {
      "year": -7750,
      "elevation": -70.6595916748047,
      "meltBp": 11399.4052734375,
      "delta10BC": 54.2685775757
    },
    {
      "year": -7500,
      "elevation": -61.399471282959,
      "meltBp": 11399.4052734375,
      "delta10BC": 63.5286979675
    },
    {
      "year": -7250,
      "elevation": -56.8465766906738,
      "meltBp": 11399.4052734375,
      "delta10BC": 68.0815925598
    },
    {
      "year": -7000,
      "elevation": -52.745059967041,
      "meltBp": 11399.4052734375,
      "delta10BC": 72.1831092834
    },
    {
      "year": -6750,
      "elevation": -47.7381439208984,
      "meltBp": 11399.4052734375,
      "delta10BC": 77.1900253296
    },
    {
      "year": -6500,
      "elevation": -42.611457824707,
      "meltBp": 11399.4052734375,
      "delta10BC": 82.3167114258
    },
    {
      "year": -6250,
      "elevation": -39.8702774047852,
      "meltBp": 11399.4052734375,
      "delta10BC": 85.0578918457
    },
    {
      "year": -6000,
      "elevation": -38.6798553466797,
      "meltBp": 11399.4052734375,
      "delta10BC": 86.2483139038
    },
    {
      "year": -5750,
      "elevation": -35.7026748657227,
      "meltBp": 11399.4052734375,
      "delta10BC": 89.2254943848
    },
    {
      "year": -5500,
      "elevation": -35.9750862121582,
      "meltBp": 11399.4052734375,
      "delta10BC": 88.9530830383
    },
    {
      "year": -5250,
      "elevation": -34.970703125,
      "meltBp": 11399.4052734375,
      "delta10BC": 89.9574661255
    },
    {
      "year": -5000,
      "elevation": -32.766845703125,
      "meltBp": 11399.4052734375,
      "delta10BC": 92.1613235474
    },
    {
      "year": -4750,
      "elevation": -32.4258193969727,
      "meltBp": 11399.4052734375,
      "delta10BC": 92.5023498535
    },
    {
      "year": -4500,
      "elevation": -29.8431262969971,
      "meltBp": 11399.4052734375,
      "delta10BC": 95.0850429535
    },
    {
      "year": -4250,
      "elevation": -28.1926002502441,
      "meltBp": 11399.4052734375,
      "delta10BC": 96.7355690002
    },
    {
      "year": -4000,
      "elevation": -25.4672718048096,
      "meltBp": 11399.4052734375,
      "delta10BC": 99.4608974457
    },
    {
      "year": -3750,
      "elevation": -22.755542755127,
      "meltBp": 11399.4052734375,
      "delta10BC": 102.1726264954
    },
    {
      "year": -3500,
      "elevation": -20.845890045166,
      "meltBp": 11399.4052734375,
      "delta10BC": 104.0822792053
    },
    {
      "year": -3250,
      "elevation": -19.4302177429199,
      "meltBp": 11399.4052734375,
      "delta10BC": 105.4979515076
    },
    {
      "year": -3000,
      "elevation": -18.1010589599609,
      "meltBp": 11399.4052734375,
      "delta10BC": 106.8271102905
    },
    {
      "year": -2750,
      "elevation": -16.1056060791016,
      "meltBp": 11399.4052734375,
      "delta10BC": 108.8225631714
    },
    {
      "year": -2500,
      "elevation": -14.1873435974121,
      "meltBp": 11399.4052734375,
      "delta10BC": 110.7408256531
    },
    {
      "year": -2250,
      "elevation": -12.3419065475464,
      "meltBp": 11399.4052734375,
      "delta10BC": 112.5862627029
    },
    {
      "year": -2000,
      "elevation": -10.5658206939697,
      "meltBp": 11399.4052734375,
      "delta10BC": 114.3623485565
    },
    {
      "year": -1750,
      "elevation": -9.00493240356445,
      "meltBp": 11399.4052734375,
      "delta10BC": 115.9232368469
    },
    {
      "year": -1500,
      "elevation": -7.40543127059937,
      "meltBp": 11399.4052734375,
      "delta10BC": 117.5227379799
    },
    {
      "year": -1250,
      "elevation": -5.07132768630981,
      "meltBp": 11399.4052734375,
      "delta10BC": 119.8568415642
    },
    {
      "year": -1000,
      "elevation": -4.58954238891602,
      "meltBp": 11399.4052734375,
      "delta10BC": 120.3386268616
    },
    {
      "year": -750,
      "elevation": -3.16532468795776,
      "meltBp": 11399.4052734375,
      "delta10BC": 121.7628445625
    },
    {
      "year": -500,
      "elevation": -1.69568371772766,
      "meltBp": 11399.4052734375,
      "delta10BC": 123.2324855328
    },
    {
      "year": -250,
      "elevation": -0.378782629966736,
      "meltBp": 11399.4052734375,
      "delta10BC": 124.5493866205
    },
    {
      "year": 0,
      "elevation": 0.988638877868652,
      "meltBp": 11399.4052734375,
      "delta10BC": 125.9168081284
    },
    {
      "year": 250,
      "elevation": 2.5053825378418,
      "meltBp": 11399.4052734375,
      "delta10BC": 127.4335517883
    },
    {
      "year": 500,
      "elevation": 4.27212619781494,
      "meltBp": 11399.4052734375,
      "delta10BC": 129.2002954483
    },
    {
      "year": 750,
      "elevation": 5.39444923400879,
      "meltBp": 11399.4052734375,
      "delta10BC": 130.3226184845
    },
    {
      "year": 1000,
      "elevation": 6.16981172561646,
      "meltBp": 11399.4052734375,
      "delta10BC": 131.0979809761
    },
    {
      "year": 1250,
      "elevation": 8.5991096496582,
      "meltBp": 11399.4052734375,
      "delta10BC": 133.5272789001
    },
    {
      "year": 1500,
      "elevation": 9.57962799072266,
      "meltBp": 11399.4052734375,
      "delta10BC": 134.5077972412
    },
    {
      "year": 1750,
      "elevation": 10.6215991973877,
      "meltBp": 11399.4052734375,
      "delta10BC": 135.5497684479
    },
    {
      "year": 2000,
      "elevation": 11.8161973953247,
      "meltBp": 11399.4052734375,
      "delta10BC": 136.7443666458
    }
  ]
}